cmk_active_check_maker/__init__.py
cmk_active_check_maker/cookiecutter_templates/cmk_active_check/cookiecutter.json
cmk_active_check_maker/cookiecutter_templates/cmk_active_check/hooks/pre_gen_project.py
cmk_active_check_maker/cookiecutter_templates/cmk_active_check/setup.py
cmk_active_check_maker/cookiecutter_templates/cmk_active_check/{{cookiecutter.agent_id}}/.bumpversion.cfg
cmk_active_check_maker/cookiecutter_templates/cmk_active_check/{{cookiecutter.agent_id}}/.gitignore
cmk_active_check_maker/cookiecutter_templates/cmk_active_check/{{cookiecutter.agent_id}}/.gitlab-ci.yml
cmk_active_check_maker/cookiecutter_templates/cmk_active_check/{{cookiecutter.agent_id}}/.pre-commit-config.yaml
cmk_active_check_maker/cookiecutter_templates/cmk_active_check/{{cookiecutter.agent_id}}/Dockerfile
cmk_active_check_maker/cookiecutter_templates/cmk_active_check/{{cookiecutter.agent_id}}/Makefile
cmk_active_check_maker/cookiecutter_templates/cmk_active_check/{{cookiecutter.agent_id}}/README.md
cmk_active_check_maker/cookiecutter_templates/cmk_active_check/{{cookiecutter.agent_id}}/active_check/agent_{{cookiecutter.agent_id}}.py
cmk_active_check_maker/cookiecutter_templates/cmk_active_check/{{cookiecutter.agent_id}}/check_invoker/agent_{{cookiecutter.agent_id}}.py
cmk_active_check_maker/cookiecutter_templates/cmk_active_check/{{cookiecutter.agent_id}}/docs/.gitkeep
cmk_active_check_maker/cookiecutter_templates/cmk_active_check/{{cookiecutter.agent_id}}/info
cmk_active_check_maker/cookiecutter_templates/cmk_active_check/{{cookiecutter.agent_id}}/info.json
cmk_active_check_maker/cookiecutter_templates/cmk_active_check/{{cookiecutter.agent_id}}/mkp_packer.py
cmk_active_check_maker/cookiecutter_templates/cmk_active_check/{{cookiecutter.agent_id}}/pyproject.toml
cmk_active_check_maker/cookiecutter_templates/cmk_active_check/{{cookiecutter.agent_id}}/run_check.py
cmk_active_check_maker/cookiecutter_templates/cmk_active_check/{{cookiecutter.agent_id}}/sample_data.json
cmk_active_check_maker-2.0.4.dist-info/METADATA
cmk_active_check_maker-2.0.4.dist-info/WHEEL
cmk_active_check_maker-2.0.4.dist-info/entry_points.txt
cmk_active_check_maker-2.0.4.dist-info/RECORD
